LICENSE
machineries/__init__.py
machineries/machine.py
machineries/main.py
machineries-0.1.1.dist-info/LICENSE
machineries-0.1.1.dist-info/METADATA
machineries-0.1.1.dist-info/WHEEL
machineries-0.1.1.dist-info/RECORD
