Metadata-Version: 2.1
Name: machineries
Version: 0.1.1
Summary: Python framework for controlling machines
Home-page: https://github.com/tadnir/machineries
License: MIT
Author: michael tadnir
Author-email: tadnir50@gmail.com
Requires-Python: >=3.6,<4.0
Classifier: License :: OSI Approved :: MIT License
Classifier: Programming Language :: Python :: 3
Classifier: Programming Language :: Python :: 3.6
Classifier: Programming Language :: Python :: 3.7
Classifier: Programming Language :: Python :: 3.8
Classifier: Programming Language :: Python :: 3.9
Classifier: Programming Language :: Python :: 3.10
Classifier: Programming Language :: Python :: 3.11
Project-URL: Repository, https://github.com/tadnir/machineries
